Metadata-Version: 2.1
Name: atlas-placement-hints
Version: 0.1.3
Summary: Library containing command lines and tools to compute placement hints
Home-page: https://github.com/BlueBrain/atlas-placement-hints
Author: Blue Brain Project, EPFL
License: Apache-2
Download-URL: https://github.com/BlueBrain/atlas-placement-hints
Platform: UNKNOWN
Classifier: Development Status :: 2 - Pre-Alpha
Classifier: Programming Language :: Python
Classifier: Programming Language :: Python :: 3
Classifier: Programming Language :: Python :: 3.7
Classifier: Programming Language :: Python :: 3.8
Classifier: Programming Language :: Python :: 3.9
Classifier: Programming Language :: Python :: 3.10
Requires-Python: >=3.7.0
Provides-Extra: tests
